textembed/__init__.py
textembed/log.py
textembed/server.py
textembed/api/__init__.py
textembed/api/dependencies.py
textembed/api/docs.py
textembed/api/embed.py
textembed/api/errors.py
textembed/api/monitor.py
textembed/api/schemas.py
textembed/application/__init__.py
textembed/application/application.py
textembed/batch/__init__.py
textembed/batch/batch_processor.py
textembed/engine/__init__.py
textembed/engine/args.py
textembed/engine/async_engine.py
textembed/engine/async_engine_array.py
textembed/executor/__init__.py
textembed/executor/base.py
textembed/executor/primitives.py
textembed/executor/embedder/__init__.py
textembed/executor/embedder/sentence_transformer.py
textembed-0.0.8.dist-info/LICENSE
textembed-0.0.8.dist-info/METADATA
textembed-0.0.8.dist-info/WHEEL
textembed-0.0.8.dist-info/top_level.txt
textembed-0.0.8.dist-info/RECORD
